{
  "top_player": {
    "id": 99,
    "points": 23
  },
  "team": [
    {
      "element": 625,
      "points": 11,
      "position": 1
    },
    {
      "element": 118,
      "points": 18,
      "position": 2
    },
    {
      "element": 236,
      "points": 15,
      "position": 3
    },
    {
      "element": 417,
      "points": 14,
      "position": 4
    },
    {
      "element": 494,
      "points": 16,
      "position": 5
    },
    {
      "element": 221,
      "points": 15,
      "position": 6
    },
    {
      "element": 223,
      "points": 15,
      "position": 7
    },
    {
      "element": 563,
      "points": 12,
      "position": 8
    },
    {
      "element": 99,
      "points": 23,
      "position": 9
    },
    {
      "element": 608,
      "points": 21,
      "position": 10
    },
    {
      "element": 439,
      "points": 17,
      "position": 11
    }
  ]
}