{
  "fixtures": [],
  "history": [
    {
      "element": 94,
      "fixture": 1,
      "opponent_team": 16,
      "total_points": 6,
      "was_home": true,
      "kickoff_time": "2025-08-28T18:00:00Z",
      "team_h_score": 1,
      "team_a_score": 0,
      "round": 1,
      "modified": false,
      "minutes": 73,
      "goals_scored": 0,
      "assists": 1,
      "clean_sheets": 1,
      "goals_conceded": 0,
      "penalties_saved": 0,
      "penalties_missed": 0,
      "yellow_cards": 0,
      "red_cards": 0,
      "saves": 0,
      "own_goals": 0,
      "bonus": 0,
      "fmmp": 0,
      "winning_goals": 0,
      "won_tackle": 0,
      "accurate_pass": 25,
      "clearances_blocks_interceptions": 5,
      "shot_target": 1,
      "big_chance_created": 1,
      "big_chance_missed": 0,
      "performance_index": 70,
      "value": 60,
      "transfers_balance": 0,
      "selected": 15792,
      "transfers_in": 0,
      "transfers_out": 0
    },
    {
      "element": 94,
      "fixture": 9,
      "opponent_team": 6,
      "total_points": 3,
      "was_home": false,
      "kickoff_time": "2025-09-12T15:25:00Z",
      "team_h_score": 0,
      "team_a_score": 0,
      "round": 2,
      "modified": false,
      "minutes": 90,
      "goals_scored": 0,
      "assists": 0,
      "clean_sheets": 1,
      "goals_conceded": 0,
      "penalties_saved": 0,
      "penalties_missed": 0,
      "yellow_cards": 0,
      "red_cards": 0,
      "saves": 0,
      "own_goals": 0,
      "bonus": 0,
      "fmmp": 0,
      "winning_goals": 0,
      "won_tackle": 1,
      "accurate_pass": 24,
      "clearances_blocks_interceptions": 2,
      "shot_target": 1,
      "big_chance_created": 0,
      "big_chance_missed": 0,
      "performance_index": 62,
      "value": 60,
      "transfers_balance": 2497,
      "selected": 23934,
      "transfers_in": 3611,
      "transfers_out": 1114
    },
    {
      "element": 94,
      "fixture": 21,
      "opponent_team": 5,
      "total_points": 4,
      "was_home": true,
      "kickoff_time": "2025-09-19T18:00:00Z",
      "team_h_score": 3,
      "team_a_score": 3,
      "round": 3,
      "modified": false,
      "minutes": 90,
      "goals_scored": 0,
      "assists": 0,
      "clean_sheets": 0,
      "goals_conceded": 3,
      "penalties_saved": 0,
      "penalties_missed": 0,
      "yellow_cards": 0,
      "red_cards": 0,
      "saves": 0,
      "own_goals": 0,
      "bonus": 0,
      "fmmp": 0,
      "winning_goals": 0,
      "won_tackle": 1,
      "accurate_pass": 43,
      "clearances_blocks_interceptions": 3,
      "shot_target": 4,
      "big_chance_created": 1,
      "big_chance_missed": 1,
      "performance_index": 64,
      "value": 60,
      "transfers_balance": -309,
      "selected": 23966,
      "transfers_in": 1135,
      "transfers_out": 1444
    },
    {
      "element": 94,
      "fixture": 34,
      "opponent_team": 17,
      "total_points": 0,
      "was_home": false,
      "kickoff_time": "2025-09-26T15:35:00Z",
      "team_h_score": 0,
      "team_a_score": 2,
      "round": 4,
      "modified": false,
      "minutes": 0,
      "goals_scored": 0,
      "assists": 0,
      "clean_sheets": 0,
      "goals_conceded": 0,
      "penalties_saved": 0,
      "penalties_missed": 0,
      "yellow_cards": 0,
      "red_cards": 0,
      "saves": 0,
      "own_goals": 0,
      "bonus": 0,
      "fmmp": 0,
      "winning_goals": 0,
      "won_tackle": 0,
      "accurate_pass": 0,
      "clearances_blocks_interceptions": 0,
      "shot_target": 0,
      "big_chance_created": 0,
      "big_chance_missed": 0,
      "performance_index": 0,
      "value": 60,
      "transfers_balance": -204,
      "selected": 24285,
      "transfers_in": 1358,
      "transfers_out": 1562
    },
    {
      "element": 94,
      "fixture": 36,
      "opponent_team": 11,
      "total_points": 2,
      "was_home": true,
      "kickoff_time": "2025-10-17T18:00:00Z",
      "team_h_score": 1,
      "team_a_score": 1,
      "round": 5,
      "modified": false,
      "minutes": 90,
      "goals_scored": 0,
      "assists": 0,
      "clean_sheets": 0,
      "goals_conceded": 1,
      "penalties_saved": 0,
      "penalties_missed": 0,
      "yellow_cards": 1,
      "red_cards": 0,
      "saves": 0,
      "own_goals": 0,
      "bonus": 0,
      "fmmp": 0,
      "winning_goals": 0,
      "won_tackle": 0,
      "accurate_pass": 40,
      "clearances_blocks_interceptions": 3,
      "shot_target": 1,
      "big_chance_created": 0,
      "big_chance_missed": 0,
      "performance_index": 76,
      "value": 60,
      "transfers_balance": -3258,
      "selected": 21093,
      "transfers_in": 245,
      "transfers_out": 3503
    },
    {
      "element": 94,
      "fixture": 45,
      "opponent_team": 18,
      "total_points": 5,
      "was_home": false,
      "kickoff_time": "2025-10-23T18:00:00Z",
      "team_h_score": 0,
      "team_a_score": 1,
      "round": 6,
      "modified": false,
      "minutes": 90,
      "goals_scored": 0,
      "assists": 0,
      "clean_sheets": 1,
      "goals_conceded": 0,
      "penalties_saved": 0,
      "penalties_missed": 0,
      "yellow_cards": 1,
      "red_cards": 0,
      "saves": 0,
      "own_goals": 0,
      "bonus": 1,
      "fmmp": 0,
      "winning_goals": 0,
      "won_tackle": 0,
      "accurate_pass": 34,
      "clearances_blocks_interceptions": 9,
      "shot_target": 3,
      "big_chance_created": 0,
      "big_chance_missed": 1,
      "performance_index": 82,
      "value": 60,
      "transfers_balance": -1764,
      "selected": 19472,
      "transfers_in": 260,
      "transfers_out": 2024
    },
    {
      "element": 94,
      "fixture": 55,
      "opponent_team": 10,
      "total_points": 3,
      "was_home": true,
      "kickoff_time": "2025-10-30T17:30:00Z",
      "team_h_score": 1,
      "team_a_score": 1,
      "round": 7,
      "modified": false,
      "minutes": 90,
      "goals_scored": 0,
      "assists": 0,
      "clean_sheets": 1,
      "goals_conceded": 0,
      "penalties_saved": 0,
      "penalties_missed": 0,
      "yellow_cards": 0,
      "red_cards": 0,
      "saves": 0,
      "own_goals": 0,
      "bonus": 0,
      "fmmp": 0,
      "winning_goals": 0,
      "won_tackle": 1,
      "accurate_pass": 30,
      "clearances_blocks_interceptions": 1,
      "shot_target": 2,
      "big_chance_created": 0,
      "big_chance_missed": 0,
      "performance_index": 72,
      "value": 60,
      "transfers_balance": -507,
      "selected": 19056,
      "transfers_in": 394,
      "transfers_out": 901
    },
    {
      "element": 94,
      "fixture": 67,
      "opponent_team": 7,
      "total_points": 3,
      "was_home": false,
      "kickoff_time": "2025-11-08T17:30:00Z",
      "team_h_score": 0,
      "team_a_score": 1,
      "round": 8,
      "modified": false,
      "minutes": 73,
      "goals_scored": 0,
      "assists": 0,
      "clean_sheets": 1,
      "goals_conceded": 0,
      "penalties_saved": 0,
      "penalties_missed": 0,
      "yellow_cards": 1,
      "red_cards": 0,
      "saves": 0,
      "own_goals": 0,
      "bonus": 0,
      "fmmp": 0,
      "winning_goals": 0,
      "won_tackle": 0,
      "accurate_pass": 12,
      "clearances_blocks_interceptions": 8,
      "shot_target": 0,
      "big_chance_created": 1,
      "big_chance_missed": 0,
      "performance_index": 59,
      "value": 60,
      "transfers_balance": -1564,
      "selected": 17477,
      "transfers_in": 81,
      "transfers_out": 1645
    },
    {
      "element": 94,
      "fixture": 73,
      "opponent_team": 14,
      "total_points": 0,
      "was_home": true,
      "kickoff_time": "2025-11-21T17:30:00Z",
      "team_h_score": 2,
      "team_a_score": 1,
      "round": 9,
      "modified": false,
      "minutes": 0,
      "goals_scored": 0,
      "assists": 0,
      "clean_sheets": 0,
      "goals_conceded": 0,
      "penalties_saved": 0,
      "penalties_missed": 0,
      "yellow_cards": 0,
      "red_cards": 0,
      "saves": 0,
      "own_goals": 0,
      "bonus": 0,
      "fmmp": 0,
      "winning_goals": 0,
      "won_tackle": 0,
      "accurate_pass": 0,
      "clearances_blocks_interceptions": 0,
      "shot_target": 0,
      "big_chance_created": 0,
      "big_chance_missed": 0,
      "performance_index": 0,
      "value": 59,
      "transfers_balance": -945,
      "selected": 16608,
      "transfers_in": 87,
      "transfers_out": 1032
    },
    {
      "element": 94,
      "fixture": 90,
      "opponent_team": 3,
      "total_points": 3,
      "was_home": false,
      "kickoff_time": "2025-12-26T13:05:00Z",
      "team_h_score": 2,
      "team_a_score": 1,
      "round": 10,
      "modified": false,
      "minutes": 78,
      "goals_scored": 0,
      "assists": 0,
      "clean_sheets": 0,
      "goals_conceded": 2,
      "penalties_saved": 0,
      "penalties_missed": 0,
      "yellow_cards": 1,
      "red_cards": 0,
      "saves": 0,
      "own_goals": 0,
      "bonus": 0,
      "fmmp": 0,
      "winning_goals": 0,
      "won_tackle": 3,
      "accurate_pass": 32,
      "clearances_blocks_interceptions": 7,
      "shot_target": 0,
      "big_chance_created": 0,
      "big_chance_missed": 0,
      "performance_index": 73,
      "value": 59,
      "transfers_balance": -680,
      "selected": 16088,
      "transfers_in": 92,
      "transfers_out": 772
    },
    {
      "element": 94,
      "fixture": 100,
      "opponent_team": 4,
      "total_points": 0,
      "was_home": true,
      "kickoff_time": "2025-12-30T15:30:00Z",
      "team_h_score": 2,
      "team_a_score": 0,
      "round": 11,
      "modified": false,
      "minutes": 0,
      "goals_scored": 0,
      "assists": 0,
      "clean_sheets": 0,
      "goals_conceded": 0,
      "penalties_saved": 0,
      "penalties_missed": 0,
      "yellow_cards": 0,
      "red_cards": 0,
      "saves": 0,
      "own_goals": 0,
      "bonus": 0,
      "fmmp": 0,
      "winning_goals": 0,
      "won_tackle": 0,
      "accurate_pass": 0,
      "clearances_blocks_interceptions": 0,
      "shot_target": 0,
      "big_chance_created": 0,
      "big_chance_missed": 0,
      "performance_index": 0,
      "value": 59,
      "transfers_balance": -1285,
      "selected": 15053,
      "transfers_in": 12,
      "transfers_out": 1297
    },
    {
      "element": 94,
      "fixture": 109,
      "opponent_team": 9,
      "total_points": 0,
      "was_home": true,
      "kickoff_time": "2026-01-02T17:30:00Z",
      "team_h_score": 3,
      "team_a_score": 2,
      "round": 12,
      "modified": false,
      "minutes": 0,
      "goals_scored": 0,
      "assists": 0,
      "clean_sheets": 0,
      "goals_conceded": 0,
      "penalties_saved": 0,
      "penalties_missed": 0,
      "yellow_cards": 0,
      "red_cards": 0,
      "saves": 0,
      "own_goals": 0,
      "bonus": 0,
      "fmmp": 0,
      "winning_goals": 0,
      "won_tackle": 0,
      "accurate_pass": 0,
      "clearances_blocks_interceptions": 0,
      "shot_target": 0,
      "big_chance_created": 0,
      "big_chance_missed": 0,
      "performance_index": 0,
      "value": 59,
      "transfers_balance": -958,
      "selected": 14103,
      "transfers_in": 5,
      "transfers_out": 963
    },
    {
      "element": 94,
      "fixture": 123,
      "opponent_team": 2,
      "total_points": 3,
      "was_home": false,
      "kickoff_time": "2026-01-10T17:30:00Z",
      "team_h_score": 0,
      "team_a_score": 1,
      "round": 13,
      "modified": false,
      "minutes": 90,
      "goals_scored": 0,
      "assists": 0,
      "clean_sheets": 1,
      "goals_conceded": 0,
      "penalties_saved": 0,
      "penalties_missed": 0,
      "yellow_cards": 1,
      "red_cards": 0,
      "saves": 0,
      "own_goals": 0,
      "bonus": 0,
      "fmmp": 0,
      "winning_goals": 0,
      "won_tackle": 0,
      "accurate_pass": 28,
      "clearances_blocks_interceptions": 9,
      "shot_target": 1,
      "big_chance_created": 1,
      "big_chance_missed": 0,
      "performance_index": 54,
      "value": 59,
      "transfers_balance": -463,
      "selected": 13651,
      "transfers_in": 15,
      "transfers_out": 478
    },
    {
      "element": 94,
      "fixture": 126,
      "opponent_team": 12,
      "total_points": 2,
      "was_home": true,
      "kickoff_time": "2026-01-14T17:30:00Z",
      "team_h_score": 2,
      "team_a_score": 1,
      "round": 14,
      "modified": false,
      "minutes": 88,
      "goals_scored": 0,
      "assists": 0,
      "clean_sheets": 0,
      "goals_conceded": 1,
      "penalties_saved": 0,
      "penalties_missed": 0,
      "yellow_cards": 1,
      "red_cards": 0,
      "saves": 0,
      "own_goals": 0,
      "bonus": 0,
      "fmmp": 0,
      "winning_goals": 0,
      "won_tackle": 0,
      "accurate_pass": 37,
      "clearances_blocks_interceptions": 9,
      "shot_target": 1,
      "big_chance_created": 0,
      "big_chance_missed": 0,
      "performance_index": 48,
      "value": 59,
      "transfers_balance": -209,
      "selected": 13448,
      "transfers_in": 10,
      "transfers_out": 219
    },
    {
      "element": 94,
      "fixture": 140,
      "opponent_team": 15,
      "total_points": 6,
      "was_home": false,
      "kickoff_time": "2026-01-17T15:10:00Z",
      "team_h_score": 0,
      "team_a_score": 1,
      "round": 15,
      "modified": false,
      "minutes": 90,
      "goals_scored": 0,
      "assists": 1,
      "clean_sheets": 1,
      "goals_conceded": 0,
      "penalties_saved": 0,
      "penalties_missed": 0,
      "yellow_cards": 1,
      "red_cards": 0,
      "saves": 0,
      "own_goals": 0,
      "bonus": 0,
      "fmmp": 0,
      "winning_goals": 0,
      "won_tackle": 0,
      "accurate_pass": 30,
      "clearances_blocks_interceptions": 7,
      "shot_target": 2,
      "big_chance_created": 0,
      "big_chance_missed": 0,
      "performance_index": 54,
      "value": 59,
      "transfers_balance": -200,
      "selected": 13255,
      "transfers_in": 20,
      "transfers_out": 220
    },
    {
      "element": 94,
      "fixture": 145,
      "opponent_team": 8,
      "total_points": 1,
      "was_home": true,
      "kickoff_time": "2026-01-20T17:30:00Z",
      "team_h_score": 4,
      "team_a_score": 1,
      "round": 16,
      "modified": false,
      "minutes": 10,
      "goals_scored": 0,
      "assists": 0,
      "clean_sheets": 0,
      "goals_conceded": 0,
      "penalties_saved": 0,
      "penalties_missed": 0,
      "yellow_cards": 0,
      "red_cards": 0,
      "saves": 0,
      "own_goals": 0,
      "bonus": 0,
      "fmmp": 0,
      "winning_goals": 0,
      "won_tackle": 1,
      "accurate_pass": 2,
      "clearances_blocks_interceptions": 1,
      "shot_target": 2,
      "big_chance_created": 0,
      "big_chance_missed": 0,
      "performance_index": 74,
      "value": 59,
      "transfers_balance": -125,
      "selected": 13135,
      "transfers_in": 26,
      "transfers_out": 151
    },
    {
      "element": 94,
      "fixture": 161,
      "opponent_team": 16,
      "total_points": 8,
      "was_home": false,
      "kickoff_time": "2026-01-24T17:30:00Z",
      "team_h_score": 0,
      "team_a_score": 3,
      "round": 17,
      "modified": false,
      "minutes": 71,
      "goals_scored": 1,
      "assists": 0,
      "clean_sheets": 1,
      "goals_conceded": 0,
      "penalties_saved": 0,
      "penalties_missed": 0,
      "yellow_cards": 0,
      "red_cards": 0,
      "saves": 0,
      "own_goals": 0,
      "bonus": 0,
      "fmmp": 0,
      "winning_goals": 0,
      "won_tackle": 0,
      "accurate_pass": 7,
      "clearances_blocks_interceptions": 2,
      "shot_target": 2,
      "big_chance_created": 0,
      "big_chance_missed": 0,
      "performance_index": 60,
      "value": 59,
      "transfers_balance": -183,
      "selected": 13018,
      "transfers_in": 13,
      "transfers_out": 196
    },
    {
      "element": 94,
      "fixture": 164,
      "opponent_team": 6,
      "total_points": 3,
      "was_home": true,
      "kickoff_time": "2026-01-28T17:30:00Z",
      "team_h_score": 4,
      "team_a_score": 0,
      "round": 18,
      "modified": false,
      "minutes": 72,
      "goals_scored": 0,
      "assists": 0,
      "clean_sheets": 1,
      "goals_conceded": 0,
      "penalties_saved": 0,
      "penalties_missed": 0,
      "yellow_cards": 0,
      "red_cards": 0,
      "saves": 0,
      "own_goals": 0,
      "bonus": 0,
      "fmmp": 0,
      "winning_goals": 0,
      "won_tackle": 0,
      "accurate_pass": 19,
      "clearances_blocks_interceptions": 4,
      "shot_target": 0,
      "big_chance_created": 1,
      "big_chance_missed": 0,
      "performance_index": 71,
      "value": 59,
      "transfers_balance": -34,
      "selected": 13176,
      "transfers_in": 74,
      "transfers_out": 108
    },
    {
      "element": 94,
      "fixture": 173,
      "opponent_team": 5,
      "total_points": 3,
      "was_home": false,
      "kickoff_time": "2026-02-02T17:30:00Z",
      "team_h_score": 0,
      "team_a_score": 0,
      "round": 19,
      "modified": false,
      "minutes": 74,
      "goals_scored": 0,
      "assists": 0,
      "clean_sheets": 1,
      "goals_conceded": 0,
      "penalties_saved": 0,
      "penalties_missed": 0,
      "yellow_cards": 0,
      "red_cards": 0,
      "saves": 0,
      "own_goals": 0,
      "bonus": 0,
      "fmmp": 0,
      "winning_goals": 0,
      "won_tackle": 0,
      "accurate_pass": 16,
      "clearances_blocks_interceptions": 0,
      "shot_target": 0,
      "big_chance_created": 0,
      "big_chance_missed": 0,
      "performance_index": 31,
      "value": 59,
      "transfers_balance": -110,
      "selected": 13067,
      "transfers_in": 16,
      "transfers_out": 126
    },
    {
      "element": 94,
      "fixture": 181,
      "opponent_team": 17,
      "total_points": 0,
      "was_home": true,
      "kickoff_time": "2026-02-05T17:30:00Z",
      "team_h_score": 2,
      "team_a_score": 0,
      "round": 20,
      "modified": false,
      "minutes": 0,
      "goals_scored": 0,
      "assists": 0,
      "clean_sheets": 0,
      "goals_conceded": 0,
      "penalties_saved": 0,
      "penalties_missed": 0,
      "yellow_cards": 0,
      "red_cards": 0,
      "saves": 0,
      "own_goals": 0,
      "bonus": 0,
      "fmmp": 0,
      "winning_goals": 0,
      "won_tackle": 0,
      "accurate_pass": 0,
      "clearances_blocks_interceptions": 0,
      "shot_target": 0,
      "big_chance_created": 0,
      "big_chance_missed": 0,
      "performance_index": 0,
      "value": 59,
      "transfers_balance": -5,
      "selected": 13090,
      "transfers_in": 97,
      "transfers_out": 102
    },
    {
      "element": 94,
      "fixture": 196,
      "opponent_team": 11,
      "total_points": 8,
      "was_home": false,
      "kickoff_time": "2026-02-13T13:55:00Z",
      "team_h_score": 2,
      "team_a_score": 5,
      "round": 21,
      "modified": false,
      "minutes": 64,
      "goals_scored": 1,
      "assists": 0,
      "clean_sheets": 0,
      "goals_conceded": 2,
      "penalties_saved": 0,
      "penalties_missed": 0,
      "yellow_cards": 1,
      "red_cards": 0,
      "saves": 0,
      "own_goals": 0,
      "bonus": 0,
      "fmmp": 0,
      "winning_goals": 0,
      "won_tackle": 0,
      "accurate_pass": 8,
      "clearances_blocks_interceptions": 6,
      "shot_target": 3,
      "big_chance_created": 1,
      "big_chance_missed": 1,
      "performance_index": 88,
      "value": 59,
      "transfers_balance": -211,
      "selected": 12864,
      "transfers_in": 14,
      "transfers_out": 225
    },
    {
      "element": 94,
      "fixture": 199,
      "opponent_team": 18,
      "total_points": 0,
      "was_home": true,
      "kickoff_time": "2026-02-19T19:00:00Z",
      "team_h_score": 4,
      "team_a_score": 1,
      "round": 22,
      "modified": false,
      "minutes": 0,
      "goals_scored": 0,
      "assists": 0,
      "clean_sheets": 0,
      "goals_conceded": 0,
      "penalties_saved": 0,
      "penalties_missed": 0,
      "yellow_cards": 0,
      "red_cards": 0,
      "saves": 0,
      "own_goals": 0,
      "bonus": 0,
      "fmmp": 0,
      "winning_goals": 0,
      "won_tackle": 0,
      "accurate_pass": 0,
      "clearances_blocks_interceptions": 0,
      "shot_target": 0,
      "big_chance_created": 0,
      "big_chance_missed": 0,
      "performance_index": 0,
      "value": 59,
      "transfers_balance": -125,
      "selected": 12745,
      "transfers_in": 15,
      "transfers_out": 140
    },
    {
      "element": 94,
      "fixture": 89,
      "opponent_team": 13,
      "total_points": 3,
      "was_home": false,
      "kickoff_time": "2026-02-23T19:00:00Z",
      "team_h_score": 0,
      "team_a_score": 1,
      "round": 23,
      "modified": false,
      "minutes": 75,
      "goals_scored": 0,
      "assists": 0,
      "clean_sheets": 1,
      "goals_conceded": 0,
      "penalties_saved": 0,
      "penalties_missed": 0,
      "yellow_cards": 0,
      "red_cards": 0,
      "saves": 0,
      "own_goals": 0,
      "bonus": 0,
      "fmmp": 0,
      "winning_goals": 0,
      "won_tackle": 0,
      "accurate_pass": 6,
      "clearances_blocks_interceptions": 1,
      "shot_target": 0,
      "big_chance_created": 0,
      "big_chance_missed": 0,
      "performance_index": 39,
      "value": 59,
      "transfers_balance": 62,
      "selected": 12808,
      "transfers_in": 141,
      "transfers_out": 79
    },
    {
      "element": 94,
      "fixture": 213,
      "opponent_team": 10,
      "total_points": 0,
      "was_home": false,
      "kickoff_time": "2026-02-26T19:00:00Z",
      "team_h_score": 0,
      "team_a_score": 1,
      "round": 24,
      "modified": false,
      "minutes": 0,
      "goals_scored": 0,
      "assists": 0,
      "clean_sheets": 0,
      "goals_conceded": 0,
      "penalties_saved": 0,
      "penalties_missed": 0,
      "yellow_cards": 0,
      "red_cards": 0,
      "saves": 0,
      "own_goals": 0,
      "bonus": 0,
      "fmmp": 0,
      "winning_goals": 0,
      "won_tackle": 0,
      "accurate_pass": 0,
      "clearances_blocks_interceptions": 0,
      "shot_target": 0,
      "big_chance_created": 0,
      "big_chance_missed": 0,
      "performance_index": 0,
      "value": 59,
      "transfers_balance": -78,
      "selected": 12735,
      "transfers_in": 21,
      "transfers_out": 99
    },
    {
      "element": 94,
      "fixture": 217,
      "opponent_team": 7,
      "total_points": 0,
      "was_home": true,
      "kickoff_time": "2026-03-06T19:00:00Z",
      "team_h_score": 3,
      "team_a_score": 1,
      "round": 25,
      "modified": false,
      "minutes": 0,
      "goals_scored": 0,
      "assists": 0,
      "clean_sheets": 0,
      "goals_conceded": 0,
      "penalties_saved": 0,
      "penalties_missed": 0,
      "yellow_cards": 0,
      "red_cards": 0,
      "saves": 0,
      "own_goals": 0,
      "bonus": 0,
      "fmmp": 0,
      "winning_goals": 0,
      "won_tackle": 0,
      "accurate_pass": 0,
      "clearances_blocks_interceptions": 0,
      "shot_target": 0,
      "big_chance_created": 0,
      "big_chance_missed": 0,
      "performance_index": 0,
      "value": 59,
      "transfers_balance": -70,
      "selected": 12664,
      "transfers_in": 5,
      "transfers_out": 75
    },
    {
      "element": 94,
      "fixture": 230,
      "opponent_team": 14,
      "total_points": 0,
      "was_home": false,
      "kickoff_time": "2026-03-13T19:00:00Z",
      "team_h_score": 3,
      "team_a_score": 2,
      "round": 26,
      "modified": false,
      "minutes": 0,
      "goals_scored": 0,
      "assists": 0,
      "clean_sheets": 0,
      "goals_conceded": 0,
      "penalties_saved": 0,
      "penalties_missed": 0,
      "yellow_cards": 0,
      "red_cards": 0,
      "saves": 0,
      "own_goals": 0,
      "bonus": 0,
      "fmmp": 0,
      "winning_goals": 0,
      "won_tackle": 0,
      "accurate_pass": 0,
      "clearances_blocks_interceptions": 0,
      "shot_target": 0,
      "big_chance_created": 0,
      "big_chance_missed": 0,
      "performance_index": 0,
      "value": 59,
      "transfers_balance": -80,
      "selected": 12585,
      "transfers_in": 3,
      "transfers_out": 83
    },
    {
      "element": 94,
      "fixture": 234,
      "opponent_team": 13,
      "total_points": 5,
      "was_home": true,
      "kickoff_time": "2026-04-04T16:15:00Z",
      "team_h_score": 3,
      "team_a_score": 0,
      "round": 27,
      "modified": false,
      "minutes": 90,
      "goals_scored": 0,
      "assists": 0,
      "clean_sheets": 1,
      "goals_conceded": 0,
      "penalties_saved": 0,
      "penalties_missed": 0,
      "yellow_cards": 0,
      "red_cards": 0,
      "saves": 0,
      "own_goals": 0,
      "bonus": 0,
      "fmmp": 0,
      "winning_goals": 0,
      "won_tackle": 1,
      "accurate_pass": 43,
      "clearances_blocks_interceptions": 6,
      "shot_target": 1,
      "big_chance_created": 0,
      "big_chance_missed": 1,
      "performance_index": 73,
      "value": 59,
      "transfers_balance": 72,
      "selected": 12758,
      "transfers_in": 115,
      "transfers_out": 43
    },
    {
      "element": 94,
      "fixture": 254,
      "opponent_team": 4,
      "total_points": 6,
      "was_home": false,
      "kickoff_time": "2026-04-08T15:55:00Z",
      "team_h_score": 1,
      "team_a_score": 1,
      "round": 27,
      "modified": false,
      "minutes": 90,
      "goals_scored": 0,
      "assists": 1,
      "clean_sheets": 0,
      "goals_conceded": 1,
      "penalties_saved": 0,
      "penalties_missed": 0,
      "yellow_cards": 0,
      "red_cards": 0,
      "saves": 0,
      "own_goals": 0,
      "bonus": 0,
      "fmmp": 0,
      "winning_goals": 0,
      "won_tackle": 1,
      "accurate_pass": 31,
      "clearances_blocks_interceptions": 2,
      "shot_target": 3,
      "big_chance_created": 1,
      "big_chance_missed": 0,
      "performance_index": 37,
      "value": 59,
      "transfers_balance": 72,
      "selected": 12758,
      "transfers_in": 115,
      "transfers_out": 43
    },
    {
      "element": 94,
      "fixture": 265,
      "opponent_team": 9,
      "total_points": 0,
      "was_home": false,
      "kickoff_time": "2026-04-29T18:00:00Z",
      "team_h_score": 2,
      "team_a_score": 0,
      "round": 30,
      "modified": false,
      "minutes": 0,
      "goals_scored": 0,
      "assists": 0,
      "clean_sheets": 0,
      "goals_conceded": 0,
      "penalties_saved": 0,
      "penalties_missed": 0,
      "yellow_cards": 0,
      "red_cards": 0,
      "saves": 0,
      "own_goals": 0,
      "bonus": 0,
      "fmmp": 0,
      "winning_goals": 0,
      "won_tackle": 0,
      "accurate_pass": 0,
      "clearances_blocks_interceptions": 0,
      "shot_target": 0,
      "big_chance_created": 0,
      "big_chance_missed": 0,
      "performance_index": 0,
      "value": 59,
      "transfers_balance": -14,
      "selected": 12512,
      "transfers_in": 24,
      "transfers_out": 38
    },
    {
      "element": 94,
      "fixture": 270,
      "opponent_team": 2,
      "total_points": 5,
      "was_home": true,
      "kickoff_time": "2026-05-03T18:00:00Z",
      "team_h_score": 4,
      "team_a_score": 0,
      "round": 31,
      "modified": false,
      "minutes": 90,
      "goals_scored": 0,
      "assists": 0,
      "clean_sheets": 1,
      "goals_conceded": 0,
      "penalties_saved": 0,
      "penalties_missed": 0,
      "yellow_cards": 0,
      "red_cards": 0,
      "saves": 0,
      "own_goals": 0,
      "bonus": 1,
      "fmmp": 0,
      "winning_goals": 0,
      "won_tackle": 0,
      "accurate_pass": 46,
      "clearances_blocks_interceptions": 5,
      "shot_target": 1,
      "big_chance_created": 0,
      "big_chance_missed": 0,
      "performance_index": 89,
      "value": 59,
      "transfers_balance": 21,
      "selected": 12536,
      "transfers_in": 66,
      "transfers_out": 45
    },
    {
      "element": 94,
      "fixture": 245,
      "opponent_team": 3,
      "total_points": 4,
      "was_home": true,
      "kickoff_time": "2026-05-06T18:00:00Z",
      "team_h_score": 3,
      "team_a_score": 1,
      "round": 31,
      "modified": false,
      "minutes": 90,
      "goals_scored": 0,
      "assists": 0,
      "clean_sheets": 0,
      "goals_conceded": 1,
      "penalties_saved": 0,
      "penalties_missed": 0,
      "yellow_cards": 0,
      "red_cards": 0,
      "saves": 0,
      "own_goals": 0,
      "bonus": 0,
      "fmmp": 0,
      "winning_goals": 0,
      "won_tackle": 4,
      "accurate_pass": 38,
      "clearances_blocks_interceptions": 10,
      "shot_target": 0,
      "big_chance_created": 0,
      "big_chance_missed": 0,
      "performance_index": 83,
      "value": 59,
      "transfers_balance": 21,
      "selected": 12536,
      "transfers_in": 66,
      "transfers_out": 45
    },
    {
      "element": 94,
      "fixture": 280,
      "opponent_team": 12,
      "total_points": 3,
      "was_home": false,
      "kickoff_time": "2026-05-11T18:00:00Z",
      "team_h_score": 1,
      "team_a_score": 2,
      "round": 32,
      "modified": false,
      "minutes": 90,
      "goals_scored": 0,
      "assists": 0,
      "clean_sheets": 0,
      "goals_conceded": 1,
      "penalties_saved": 0,
      "penalties_missed": 0,
      "yellow_cards": 1,
      "red_cards": 0,
      "saves": 0,
      "own_goals": 0,
      "bonus": 0,
      "fmmp": 0,
      "winning_goals": 0,
      "won_tackle": 3,
      "accurate_pass": 36,
      "clearances_blocks_interceptions": 5,
      "shot_target": 3,
      "big_chance_created": 0,
      "big_chance_missed": 0,
      "performance_index": 75,
      "value": 59,
      "transfers_balance": -16,
      "selected": 12519,
      "transfers_in": 13,
      "transfers_out": 29
    },
    {
      "element": 94,
      "fixture": 289,
      "opponent_team": 15,
      "total_points": 12,
      "was_home": true,
      "kickoff_time": "2026-05-16T18:00:00Z",
      "team_h_score": 3,
      "team_a_score": 0,
      "round": 33,
      "modified": false,
      "minutes": 90,
      "goals_scored": 1,
      "assists": 0,
      "clean_sheets": 1,
      "goals_conceded": 0,
      "penalties_saved": 0,
      "penalties_missed": 0,
      "yellow_cards": 0,
      "red_cards": 0,
      "saves": 0,
      "own_goals": 0,
      "bonus": 3,
      "fmmp": 0,
      "winning_goals": 0,
      "won_tackle": 4,
      "accurate_pass": 39,
      "clearances_blocks_interceptions": 5,
      "shot_target": 1,
      "big_chance_created": 0,
      "big_chance_missed": 0,
      "performance_index": 95,
      "value": 59,
      "transfers_balance": -15,
      "selected": 12507,
      "transfers_in": 14,
      "transfers_out": 29
    },
    {
      "element": 94,
      "fixture": 301,
      "opponent_team": 8,
      "total_points": 5,
      "was_home": false,
      "kickoff_time": "2026-05-20T18:00:00Z",
      "team_h_score": 1,
      "team_a_score": 4,
      "round": 34,
      "modified": false,
      "minutes": 90,
      "goals_scored": 0,
      "assists": 0,
      "clean_sheets": 0,
      "goals_conceded": 1,
      "penalties_saved": 0,
      "penalties_missed": 0,
      "yellow_cards": 0,
      "red_cards": 0,
      "saves": 0,
      "own_goals": 0,
      "bonus": 0,
      "fmmp": 0,
      "winning_goals": 0,
      "won_tackle": 1,
      "accurate_pass": 52,
      "clearances_blocks_interceptions": 13,
      "shot_target": 1,
      "big_chance_created": 1,
      "big_chance_missed": 0,
      "performance_index": 82,
      "value": 59,
      "transfers_balance": 106,
      "selected": 12625,
      "transfers_in": 122,
      "transfers_out": 16
    }
  ],
  "history_past": []
}